{
  "source": "ruRU",
  "key": "343926cf-edee-4072-a961-ff43306641b7",
  "ownerGuid": "c76730aada944d86adf3140e51e30577",
  "languages": [
    {
      "locale": "ruRU",
      "text": "{n}{d|Encyclopedia:Ch3_EmptyPit}Кучка ничтожных выродков{/d} — все, что осталось от обитателей логова. Они слишком боятся улиц Комморры, чтобы покинуть ставшее небезопасным убежище.{/n}",
      "modification_date": "2023-12-29T12:34:56.5278006+00:00",
      "traits": []
    },
    {
      "locale": "enGB",
      "text": "{n}A {d|Encyclopedia:Ch3_EmptyPit}gaggle of pathetic weaklings{/d} are all that is left of the denizens of this hideout. They are too terrified of the streets of Commorragh to leave this shelter, as unsafe as it has become.{/n}",
      "modification_date": "2024-01-25T09:40:12.6231854+00:00",
      "translated_from": "ruRU",
      "translation_date": "2024-01-25T09:40:12.6231857+00:00",
      "original_text": "{n}{d|Encyclopedia:Ch3_EmptyPit}Кучка ничтожных выродков{/d} — все, что осталось от обитателей логова. Они слишком боятся улиц Комморры, чтобы покинуть ставшее небезопасным убежище.{/n}",
      "traits": [
        {
          "trait": "Translated",
          "trait_date": "2023-05-15T11:59:27.557103+03:00",
          "locale_text": "{n}A gaggle of pathetic weaklings are all that is left from the denizens of this hideout. They are too terrified of the streets of Commorragh to leave this shelter, as unsafe as it has become.{/n}"
        },
        {
          "trait": "TK_tr",
          "trait_date": "2023-05-15T11:59:27.5571034+03:00",
          "locale_text": "{n}A gaggle of pathetic weaklings are all that is left from the denizens of this hideout. They are too terrified of the streets of Commorragh to leave this shelter, as unsafe as it has become.{/n}"
        },
        {
          "trait": "Edited",
          "trait_date": "2023-09-01T14:39:15.280134+00:00",
          "locale_text": "{n}A gaggle of pathetic weaklings are all that is left from the denizens of this hideout. They are too terrified of the streets of Commorragh to leave this shelter, as unsafe as it has become.{/n}"
        },
        {
          "trait": "LG_ed",
          "trait_date": "2023-09-01T14:39:15.2801344+00:00",
          "locale_text": "{n}A gaggle of pathetic weaklings are all that is left from the denizens of this hideout. They are too terrified of the streets of Commorragh to leave this shelter, as unsafe as it has become.{/n}"
        },
        {
          "trait": "AD_rv",
          "trait_date": "2024-01-25T09:40:12.6231869+00:00",
          "locale_text": "{n}A {d|Encyclopedia:Ch3_EmptyPit}gaggle of pathetic weaklings{/d} are all that is left of the denizens of this hideout. They are too terrified of the streets of Commorragh to leave this shelter, as unsafe as it has become.{/n}"
        },
        {
          "trait": "Turkish",
          "trait_date": "2024-02-26T18:04:21.1354757+00:00",
          "locale_text": "{n}A {d|Encyclopedia:Ch3_EmptyPit}gaggle of pathetic weaklings{/d} are all that is left of the denizens of this hideout. They are too terrified of the streets of Commorragh to leave this shelter, as unsafe as it has become.{/n}"
        }
      ]
    },
    {
      "locale": "jaJP",
      "text": "{n}この隠れ家の住人に残されたのは、{d|Encyclopedia:Ch3_EmptyPit}哀れな弱虫たち{/d}だけだ。彼らはコモラフの街を恐れるあまり、治安が悪くなったこの隠れ家から出ることができないままでいるのだ。{/n}",
      "modification_date": "2024-05-21T08:28:24.0337847+00:00",
      "translated_from": "enGB",
      "translation_date": "2025-03-06T14:30:43.029002+00:00",
      "original_text": "{n}A {d|Encyclopedia:Ch3_EmptyPit}gaggle of pathetic weaklings{/d} are all that is left of the denizens of this hideout. They are too terrified of the streets of Commorragh to leave this shelter, as unsafe as it has become.{/n}",
      "traits": [
        {
          "trait": "Translated",
          "trait_date": "2025-03-06T14:30:43.0290025+00:00",
          "locale_text": "{n}この隠れ家の住人に残されたのは、{d|Encyclopedia:Ch3_EmptyPit}哀れな弱虫たち{/d}だけだ。彼らはコモラフの街を恐れるあまり、治安が悪くなったこの隠れ家から出ることができないままでいるのだ。{/n}"
        }
      ]
    },
    {
      "locale": "zhCN",
      "text": "{n}这个藏身处的居民{d|Encyclopedia:Ch3_EmptyPit}只剩下一群可怜的弱者{/d}。尽管这里已经不再安全，但这些人还是不敢离开这间避难所，因为科摩罗的街道把他们吓破了胆。{/n}",
      "modification_date": "2024-05-21T08:28:41.1249638+00:00",
      "translated_from": "enGB",
      "translation_date": "2024-05-21T08:28:41.1249641+00:00",
      "original_text": "{n}A {d|Encyclopedia:Ch3_EmptyPit}gaggle of pathetic weaklings{/d} are all that is left of the denizens of this hideout. They are too terrified of the streets of Commorragh to leave this shelter, as unsafe as it has become.{/n}",
      "traits": [
        {
          "trait": "Translated",
          "trait_date": "2023-10-19T13:01:05.9224644+00:00",
          "locale_text": "{n}这个藏身处的居民只剩下一群可怜的弱者。尽管这里已经不再安全，但这些人还是不敢离开这间避难所，因为科摩罗的街道把他们吓破了胆。{/n}"
        }
      ]
    },
    {
      "locale": "esES",
      "text": "{n}Una {d|Encyclopedia:Ch3_EmptyPit}pandilla de debiluchos patéticos{/d} es todo lo que queda de los habitantes de este escondite. Están demasiado aterrorizados por las calles de Commorragh como para abandonar este refugio a pesar de lo inseguro que se ha vuelto.{/n}",
      "modification_date": "2024-10-10T17:14:52.4906991+00:00",
      "translated_from": "enGB",
      "translation_date": "2023-11-21T22:57:09.4516543+00:00",
      "original_text": "{n}A {d|Encyclopedia:Ch3_EmptyPit}gaggle of pathetic weaklings{/d} are all that is left of the denizens of this hideout. They are too terrified of the streets of Commorragh to leave this shelter, as unsafe as it has become.{/n}",
      "traits": [
        {
          "trait": "Translated",
          "trait_date": "2023-11-21T22:57:09.4516559+00:00",
          "locale_text": "{n}Una pandilla de debiluchos patéticos es todo lo que queda de los habitantes de este escondite. Están demasiado aterrorizados por las calles de Commorragh como para abandonar este refugio a pesar de lo inseguro que se ha vuelto.{/n}"
        }
      ]
    },
    {
      "locale": "deDE",
      "text": "{n}Von den Bewohnern dieses Verstecks ist nur noch eine {d|Encyclopedia:Ch3_EmptyPit}kleine Gruppe Schwächlinge{/d} übrig. Sie haben zu große Angst vor den Straßen Commorraghs, um diesen Unterschlupf zu verlassen, so unsicher er auch geworden sein mag.{/n}",
      "modification_date": "2024-12-13T14:24:36.7878639+00:00",
      "translated_from": "enGB",
      "translation_date": "2023-10-17T09:10:34.7774483+00:00",
      "original_text": "{n}A {d|Encyclopedia:Ch3_EmptyPit}gaggle of pathetic weaklings{/d} are all that is left of the denizens of this hideout. They are too terrified of the streets of Commorragh to leave this shelter, as unsafe as it has become.{/n}",
      "traits": [
        {
          "trait": "Translated",
          "trait_date": "2023-10-17T09:10:34.7774498+00:00",
          "locale_text": "{n}Von den Bewohnern dieses Verstecks ist nur noch eine kleine Gruppe Schwächlinge übrig. Sie haben zu große Angst vor den Straßen Commorraghs, um diesen Unterschlupf zu verlassen, so unsicher er auch geworden sein mag.{/n}"
        },
        {
          "trait": "сами",
          "trait_date": "2024-12-09T13:02:30.7962004+00:00",
          "locale_text": "{n}Von den Bewohnern dieses Verstecks ist nur noch eine kleine Gruppe Schwächlinge übrig. Sie haben zu große Angst vor den Straßen Commorraghs, um diesen Unterschlupf zu verlassen, so unsicher er auch geworden sein mag.{/n}"
        }
      ]
    },
    {
      "locale": "frFR",
      "text": "{n}Tout ce qui reste des occupants de cet abri est un {d|Encyclopedia:Ch3_EmptyPit}petit attroupement malingre{/d} trop terrifié pour se risquer dans les rues de Commorragh, même si rester sur place est devenu encore plus dangereux.{/n}",
      "modification_date": "2024-03-13T06:52:06.8058404+00:00",
      "translated_from": "enGB",
      "translation_date": "2024-03-13T06:52:06.8058409+00:00",
      "original_text": "{n}A {d|Encyclopedia:Ch3_EmptyPit}gaggle of pathetic weaklings{/d} are all that is left of the denizens of this hideout. They are too terrified of the streets of Commorragh to leave this shelter, as unsafe as it has become.{/n}",
      "traits": [
        {
          "trait": "Translated",
          "trait_date": "2024-03-13T06:52:06.8058423+00:00",
          "locale_text": "{n}Tout ce qui reste des occupants de cet abri est un {d|Encyclopedia:Ch3_EmptyPit}petit attroupement malingre{/d} trop terrifié pour se risquer dans les rues de Commorragh, même si rester sur place est devenu encore plus dangereux.{/n}"
        }
      ]
    },
    {
      "locale": "trTR",
      "text": "{n}Bu sığınakta bir tek {d|Encyclopedia:Ch3_EmptyPit}güçsüz ve acınası bir grup{/d} kalmış. Commorragh sokaklarından çok korkuyorlar, dolayısıyla ne kadar tehlikeli olursa olsun bu sığınaktan çıkamıyorlar.{/n}",
      "modification_date": "2024-11-15T12:05:57.9333011+00:00",
      "translated_from": "enGB",
      "translation_date": "2024-11-15T12:05:57.933302+00:00",
      "original_text": "{n}A {d|Encyclopedia:Ch3_EmptyPit}gaggle of pathetic weaklings{/d} are all that is left of the denizens of this hideout. They are too terrified of the streets of Commorragh to leave this shelter, as unsafe as it has become.{/n}",
      "traits": [
        {
          "trait": "Translated",
          "trait_date": "2024-05-20T01:32:03.6588999+00:00",
          "locale_text": "{n}Bu sığınakta geriye sadece {d|Encyclopedia:Ch3_EmptyPit}güçsüz ve acınası bir grup{/d} kalmış. Commorragh sokaklarından çok korktukları için, ne kadar tehlikeli olursa olsun bu sığınaktan çıkamıyorlar.{/n}"
        }
      ]
    }
  ],
  "string_traits": []
}