{
  "source": "ruRU",
  "key": "3386d94b-3971-4b53-8c22-f8f49c118b76",
  "ownerGuid": "bc039c83f91c4932a54566bd76b1f7b9",
  "languages": [
    {
      "locale": "ruRU",
      "text": "\"Мне нужно подумать, жди здесь\".",
      "modification_date": "2024-12-20T19:39:47.3087993+00:00"
    },
    {
      "locale": "enGB",
      "text": "\"I must think this over. Wait here.\"",
      "modification_date": "2025-01-13T15:24:38.9665083+00:00",
      "translated_from": "ruRU",
      "translation_date": "2025-01-20T11:12:46.1184013+00:00",
      "original_text": "\"Мне нужно подумать, жди здесь\".",
      "traits": [
        {
          "trait": "Translated",
          "trait_date": "2025-01-13T15:24:38.9665118+00:00",
          "locale_text": "\"I must think this over. Wait here.\""
        },
        {
          "trait": "TK_tr",
          "trait_date": "2025-01-13T15:24:38.9665125+00:00",
          "locale_text": "\"I must think this over. Wait here.\""
        },
        {
          "trait": "Edited",
          "trait_date": "2025-01-20T10:20:18.2342491+00:00",
          "locale_text": "\"I must think this over. Wait here.\""
        },
        {
          "trait": "AD_ed",
          "trait_date": "2025-01-20T10:20:18.2342493+00:00",
          "locale_text": "\"I must think this over. Wait here.\""
        },
        {
          "trait": "Reviewed",
          "trait_date": "2025-01-20T11:12:46.118403+00:00",
          "locale_text": "\"I must think this over. Wait here.\""
        },
        {
          "trait": "TK_rv",
          "trait_date": "2025-01-20T11:12:46.1184035+00:00",
          "locale_text": "\"I must think this over. Wait here.\""
        }
      ]
    },
    {
      "locale": "zhCN",
      "text": "“我得仔细考虑考虑，你先等着吧。”",
      "modification_date": "2025-04-18T15:04:40.7776025+00:00",
      "translated_from": "enGB",
      "translation_date": "2025-04-18T15:04:40.7776026+00:00",
      "original_text": "\"I must think this over. Wait here.\"",
      "traits": [
        {
          "trait": "Translated",
          "trait_date": "2025-04-18T15:04:40.7776035+00:00",
          "locale_text": "“我得仔细考虑考虑，你先等着吧。”"
        }
      ]
    },
    {
      "locale": "jaJP",
      "text": "「よく考えなければならない。ここで待て」",
      "modification_date": "2025-04-21T10:14:27.8046384+00:00",
      "translated_from": "enGB",
      "translation_date": "2025-04-28T07:36:35.2744821+00:00",
      "original_text": "\"I must think this over. Wait here.\"",
      "traits": [
        {
          "trait": "Translated",
          "trait_date": "2025-04-28T07:36:35.2744825+00:00",
          "locale_text": "「よく考えなければならない。ここで待て」"
        }
      ]
    },
    {
      "locale": "esES",
      "text": "«Debo reflexionar sobre esto. Espera aquí».",
      "modification_date": "2025-04-25T13:35:47.2261134+00:00",
      "translated_from": "enGB",
      "translation_date": "2025-04-25T13:35:47.2261136+00:00",
      "original_text": "\"I must think this over. Wait here.\"",
      "traits": [
        {
          "trait": "Translated",
          "trait_date": "2025-04-25T13:35:47.2261154+00:00",
          "locale_text": "«Debo reflexionar sobre esto. Espera aquí»."
        }
      ]
    },
    {
      "locale": "trTR",
      "text": "\"Bunu bir düşüneyim. Beni burada bekle.\"",
      "modification_date": "2025-04-25T15:46:16.0867353+00:00",
      "translated_from": "enGB",
      "translation_date": "2025-04-25T15:46:16.0867355+00:00",
      "original_text": "\"I must think this over. Wait here.\"",
      "traits": [
        {
          "trait": "Translated",
          "trait_date": "2025-04-25T15:46:16.0867359+00:00",
          "locale_text": "\"Bunu bir düşüneyim. Beni burada bekle.\""
        }
      ]
    },
    {
      "locale": "frFR",
      "text": "« Il me faut y réfléchir. Attendez ici. »",
      "modification_date": "2025-04-28T07:39:06.2366072+00:00",
      "translated_from": "enGB",
      "translation_date": "2025-04-28T07:39:06.2366073+00:00",
      "original_text": "\"I must think this over. Wait here.\"",
      "traits": [
        {
          "trait": "Translated",
          "trait_date": "2025-04-28T07:39:06.2366078+00:00",
          "locale_text": "« Il me faut y réfléchir. Attendez ici. »"
        }
      ]
    },
    {
      "locale": "deDE",
      "text": "\"Ich muss nachdenken. Wartet hier.\"",
      "modification_date": "2025-05-13T07:34:18.3533417+00:00",
      "translated_from": "enGB",
      "translation_date": "2025-05-13T07:34:18.3533419+00:00",
      "original_text": "\"I must think this over. Wait here.\"",
      "traits": [
        {
          "trait": "Translated",
          "trait_date": "2025-05-13T07:34:18.3533424+00:00",
          "locale_text": "\"Ich muss nachdenken. Wartet hier.\""
        }
      ]
    }
  ],
  "string_traits": [
    {
      "trait": "DLC2",
      "trait_date": "2025-04-03T11:31:08.4662977+00:00",
      "locale_text": ""
    },
    {
      "trait": "DLC2_lore",
      "trait_date": "2025-04-03T11:31:08.4662982+00:00",
      "locale_text": ""
    },
    {
      "trait": "Sent_translation",
      "trait_date": "2025-01-14T08:40:50.4377877+00:00",
      "locale_text": ""
    },
    {
      "trait": "Sent_editing",
      "trait_date": "2025-01-14T08:40:50.4377878+00:00",
      "locale_text": ""
    },
    {
      "trait": "тассера_03апр",
      "trait_date": "2025-04-03T11:30:42.1672564+00:00",
      "locale_text": ""
    },
    {
      "trait": "DLC_SentOtherLocs",
      "trait_date": "2025-04-28T13:08:34.1460403+00:00",
      "locale_text": ""
    }
  ]
}