{
  "source": "ruRU",
  "key": "15b5f2e4-1cef-42bd-9ff3-8500617d689e",
  "ownerGuid": "e3d12d28e1f940fa8e2e756b36f469f7",
  "languages": [
    {
      "locale": "ruRU",
      "text": "Старые пряхи сплетают нить вюрда жестоко,\nНе вопрошая и не принимая мольбы.\nБросил свой взгляд Громогласный Ульфар и ясно увидел...\"",
      "modification_date": "2023-06-01T07:27:12.9179863+00:00",
      "traits": []
    },
    {
      "locale": "enGB",
      "text": "The old spinners weave\nthe wyrd-thread cruelly,\nno enquiries or entreaties accepting.\nUlfar Thunderlung cast his gaze\nand clearly he beheld...\"",
      "modification_date": "2023-08-12T05:15:57.221936+00:00",
      "translated_from": "ruRU",
      "translation_date": "2023-08-12T05:15:57.2219366+00:00",
      "original_text": "Старые пряхи сплетают нить вюрда жестоко,\nНе вопрошая и не принимая мольбы.\nБросил свой взгляд Громогласный Ульфар и ясно увидел...\"",
      "traits": [
        {
          "trait": "Translated",
          "trait_date": "2023-08-12T05:15:57.2219393+00:00",
          "locale_text": "The old spinners weave\nthe wyrd-thread cruelly,\nno enquiries or entreaties accepting.\nUlfar Thunderlung cast his gaze\nand clearly he beheld...\"",
          "speaker": "",
          "speaker_gender": ""
        },
        {
          "trait": "AD_tr_ed",
          "trait_date": "2023-08-12T05:15:57.2219397+00:00",
          "locale_text": "The old spinners weave\nthe wyrd-thread cruelly,\nno enquiries or entreaties accepting.\nUlfar Thunderlung cast his gaze\nand clearly he beheld...\"",
          "speaker": "",
          "speaker_gender": ""
        },
        {
          "trait": "Edited",
          "trait_date": "2023-07-21T17:28:30.1773938+03:00",
          "locale_text": "Старые пряхи сплетают нить вюрда жестоко,\nНе вопрошая и не принимая мольбы.\nБросил свой взгляд Громогласный Ульфар и ясно увидел...\"",
          "speaker": "",
          "speaker_gender": ""
        },
        {
          "trait": "Turkish",
          "trait_date": "2024-02-26T15:27:12.882217+00:00",
          "locale_text": "The old spinners weave\nthe wyrd-thread cruelly,\nno enquiries or entreaties accepting.\nUlfar Thunderlung cast his gaze\nand clearly he beheld...\"",
          "speaker": "",
          "speaker_gender": ""
        }
      ]
    },
    {
      "locale": "jaJP",
      "text": "年老いた紡ぎ手は\n残酷な運命の糸を編み\n問いも懇願も受け入れない。\nウルファー・サンダーラングは視線を投げかけ\nその目ではっきりと見た…」",
      "modification_date": "2025-07-14T14:39:15.2256271+00:00",
      "translated_from": "enGB",
      "translation_date": "2025-07-14T14:39:15.2256272+00:00",
      "original_text": "The old spinners weave\nthe wyrd-thread cruelly,\nno enquiries or entreaties accepting.\nUlfar Thunderlung cast his gaze\nand clearly he beheld...\"",
      "traits": [
        {
          "trait": "Translated",
          "trait_date": "2025-07-14T14:39:15.2256278+00:00",
          "locale_text": "年老いた紡ぎ手は\n残酷な運命の糸を編み\n問いも懇願も受け入れない。\nウルファー・サンダーラングは視線を投げかけ\nその目ではっきりと見た…」",
          "speaker": "",
          "speaker_gender": ""
        }
      ]
    },
    {
      "locale": "zhCN",
      "text": "“白发苍苍的女神，\n编织着残酷的命运，\n不回答任何询问，\n也不同情任何恳求。\n乌尔法·雷狼清楚地看到……”",
      "modification_date": "2023-08-24T09:36:21.3513599+00:00",
      "translated_from": "enGB",
      "translation_date": "2023-08-24T09:36:21.3513602+00:00",
      "original_text": "The old spinners weave\nthe wyrd-thread cruelly,\nno enquiries or entreaties accepting.\nUlfar Thunderlung cast his gaze\nand clearly he beheld...\"",
      "traits": [
        {
          "trait": "Translated",
          "trait_date": "2023-08-24T09:36:21.3513612+00:00",
          "locale_text": "“白发苍苍的女神，\n编织着残酷的命运，\n不回答任何询问，\n也不同情任何恳求。\n乌尔法·雷狼清楚地看到……”",
          "speaker": "",
          "speaker_gender": ""
        }
      ]
    },
    {
      "locale": "frFR",
      "text": "« Les vieilles fileuses tissent\ncruellement le fil du wyrd,\nsourdes aux suppliques des infortunés.\nUlfar Voix-du-Tonnerre lança alors un regard\nqui lui révéla clairement... »",
      "modification_date": "2023-10-17T19:30:20.0253578+00:00",
      "translated_from": "enGB",
      "translation_date": "2023-10-17T19:30:20.0253583+00:00",
      "original_text": "The old spinners weave\nthe wyrd-thread cruelly,\nno enquiries or entreaties accepting.\nUlfar Thunderlung cast his gaze\nand clearly he beheld...\"",
      "traits": [
        {
          "trait": "Translated",
          "trait_date": "2023-10-17T19:30:20.0253609+00:00",
          "locale_text": "« Les vieilles fileuses tissent\ncruellement le fil du wyrd,\nsourdes aux suppliques des infortunés.\nUlfar Voix-du-Tonnerre lança alors un regard\nqui lui révéla clairement... »",
          "speaker": "",
          "speaker_gender": ""
        }
      ]
    },
    {
      "locale": "esES",
      "text": "Las viejas hilanderas tejen\nel hilo del sino con crueldad,\nsin ceder a súplicas ni demandas.\nUlfar Pulmón Atronador levantó la mirada\ny vio con claridad...».",
      "modification_date": "2023-09-24T09:35:20.8435411+00:00",
      "translated_from": "enGB",
      "translation_date": "2023-09-24T09:35:20.8435413+00:00",
      "original_text": "The old spinners weave\nthe wyrd-thread cruelly,\nno enquiries or entreaties accepting.\nUlfar Thunderlung cast his gaze\nand clearly he beheld...\"",
      "traits": [
        {
          "trait": "Translated",
          "trait_date": "2023-09-24T09:35:20.8435425+00:00",
          "locale_text": "Las viejas hilanderas tejen\nel hilo del sino con crueldad,\nsin ceder a súplicas ni demandas.\nUlfar Pulmón Atronador levantó la mirada\ny vio con claridad...».",
          "speaker": "",
          "speaker_gender": ""
        }
      ]
    },
    {
      "locale": "deDE",
      "text": "Die alten Spinner weben\nden Wyrd-Faden grausam,\nakzeptieren keine Bitten, kein Flehen.\nUlfar Donnerlunge lenkte seinen Blick\nund ganz deutlich sah er ...\"",
      "modification_date": "2023-10-17T09:47:50.8339762+00:00",
      "translated_from": "enGB",
      "translation_date": "2023-10-17T09:47:50.8339767+00:00",
      "original_text": "The old spinners weave\nthe wyrd-thread cruelly,\nno enquiries or entreaties accepting.\nUlfar Thunderlung cast his gaze\nand clearly he beheld...\"",
      "traits": [
        {
          "trait": "Translated",
          "trait_date": "2023-10-17T09:47:50.83398+00:00",
          "locale_text": "Die alten Spinner weben\nden Wyrd-Faden grausam,\nakzeptieren keine Bitten, kein Flehen.\nUlfar Donnerlunge lenkte seinen Blick\nund ganz deutlich sah er ...\"",
          "speaker": "",
          "speaker_gender": ""
        }
      ]
    },
    {
      "locale": "trTR",
      "text": "Ne soru ne de niyaz kabul eden\nYaşlı çıkrıkçılar, örmüş\nKader ağını acımasızca.\nUlfar Tufanciğer dikkatle\nÇevirdi bakışlarını...\"",
      "modification_date": "2024-11-15T12:06:56.7293142+00:00",
      "translated_from": "enGB",
      "translation_date": "2024-11-15T12:06:56.7293149+00:00",
      "original_text": "The old spinners weave\nthe wyrd-thread cruelly,\nno enquiries or entreaties accepting.\nUlfar Thunderlung cast his gaze\nand clearly he beheld...\"",
      "traits": [
        {
          "trait": "Translated",
          "trait_date": "2024-05-20T01:32:15.2880625+00:00",
          "locale_text": "Yaşlı çıkrıkçılar örmüş,\nkader ağını acımasızca.\nHiçbir soru ve niyazı kabul etmeden.\nUlfar Tufanciğer dikkatle\nbakışlarını çevirdi...\"",
          "speaker": "",
          "speaker_gender": ""
        }
      ]
    }
  ],
  "string_traits": []
}