{
  "source": "ruRU",
  "key": "2aa11a56-351a-434c-9c46-7318a50acc1b",
  "speaker": "DrukhariBandit",
  "speakerGender": "Male",
  "ownerGuid": "19f4ecd1a0f241e9b3f5702f628d87e9",
  "languages": [
    {
      "locale": "ruRU",
      "text": "\"Бесхребетная падаль!\" {n}Один из ксеносов, наблюдавших за Ирлиэт, подается вперед и срывает с груди мертвой эльдарки пылающий алым драгоценный камень.{/n} \"По крайней мере мне хватит эманаций ее вечно страдающей души. Прочь с дороги, мон-кай!\"",
      "modification_date": "2023-03-19T17:38:03.5965485+00:00",
      "traits": [
        {
          "trait": "CheckMe",
          "trait_date": "2023-03-19T17:38:03.5965485+00:00",
          "locale_text": "\"Бесхребетная падаль!\" {n}Один из ксеносов, наблюдавших за Ирлиэт, подается вперед и срывает с груди мертвой эльдарки пылающий алым драгоценный камень.{/n} \"По крайней мере мне хватит эманаций ее вечно страдающей души. Прочь с дороги, мон-кай!\"",
          "speaker": "DrukhariBandit",
          "speaker_gender": "Male"
        }
      ]
    },
    {
      "locale": "enGB",
      "text": "\"Spineless carrion!\" {n}One of the xenos who were observing Yrliet leans forward and tears the radiant crimson gemstone from her chest.{/n} \"At least I will savour the emanations of her soul's eternal agony. Out of my way, mon-keigh!\"",
      "modification_date": "2023-05-15T11:59:27.8749603+03:00",
      "translated_from": "ruRU",
      "translation_date": "2024-01-25T09:40:14.0494399+00:00",
      "original_text": "\"Бесхребетная падаль!\" {n}Один из ксеносов, наблюдавших за Ирлиэт, подается вперед и срывает с груди мертвой эльдарки пылающий алым драгоценный камень.{/n} \"По крайней мере мне хватит эманаций ее вечно страдающей души. Прочь с дороги, мон-кай!\"",
      "traits": [
        {
          "trait": "Translated",
          "trait_date": "2023-05-15T11:59:27.8749618+03:00",
          "locale_text": "\"Spineless carrion!\" {n}One of the xenos who were observing Yrliet leans forward and tears the radiant crimson gemstone from her chest.{/n} \"At least I will savour the emanations of her soul's eternal agony. Out of my way, mon-keigh!\"",
          "speaker": "DrukhariBandit",
          "speaker_gender": "Male"
        },
        {
          "trait": "TK_tr",
          "trait_date": "2023-05-15T11:59:27.8749622+03:00",
          "locale_text": "\"Spineless carrion!\" {n}One of the xenos who were observing Yrliet leans forward and tears the radiant crimson gemstone from her chest.{/n} \"At least I will savour the emanations of her soul's eternal agony. Out of my way, mon-keigh!\"",
          "speaker": "DrukhariBandit",
          "speaker_gender": "Male"
        },
        {
          "trait": "Edited",
          "trait_date": "2023-09-01T14:38:51.1852655+00:00",
          "locale_text": "\"Spineless carrion!\" {n}One of the xenos who were observing Yrliet leans forward and tears the radiant crimson gemstone from her chest.{/n} \"At least I will savour the emanations of her soul's eternal agony. Out of my way, mon-keigh!\"",
          "speaker": "DrukhariBandit",
          "speaker_gender": "Male"
        },
        {
          "trait": "LG_ed",
          "trait_date": "2023-09-01T14:38:51.1852658+00:00",
          "locale_text": "\"Spineless carrion!\" {n}One of the xenos who were observing Yrliet leans forward and tears the radiant crimson gemstone from her chest.{/n} \"At least I will savour the emanations of her soul's eternal agony. Out of my way, mon-keigh!\"",
          "speaker": "DrukhariBandit",
          "speaker_gender": "Male"
        },
        {
          "trait": "AD_rv",
          "trait_date": "2024-01-25T09:40:14.049441+00:00",
          "locale_text": "\"Spineless carrion!\" {n}One of the xenos who were observing Yrliet leans forward and tears the radiant crimson gemstone from her chest.{/n} \"At least I will savour the emanations of her soul's eternal agony. Out of my way, mon-keigh!\"",
          "speaker": "DrukhariBandit",
          "speaker_gender": "Male"
        },
        {
          "trait": "Turkish",
          "trait_date": "2024-02-26T18:04:21.6363518+00:00",
          "locale_text": "\"Spineless carrion!\" {n}One of the xenos who were observing Yrliet leans forward and tears the radiant crimson gemstone from her chest.{/n} \"At least I will savour the emanations of her soul's eternal agony. Out of my way, mon-keigh!\"",
          "speaker": "DrukhariBandit",
          "speaker_gender": "Male"
        }
      ]
    },
    {
      "locale": "jaJP",
      "text": "「薄汚い腰抜けめ！」{n}ユリエットを観察していた異種族のひとりが身を乗り出し、彼女の胸から輝く真紅の宝石を引きちぎる。{/n}「この女の魂の永遠の苦しみだけでも味わってやろう。どけ、モン＝ケイ！」",
      "modification_date": "2025-03-06T14:30:46.7339394+00:00",
      "translated_from": "enGB",
      "translation_date": "2025-03-06T14:30:46.7339395+00:00",
      "original_text": "\"Spineless carrion!\" {n}One of the xenos who were observing Yrliet leans forward and tears the radiant crimson gemstone from her chest.{/n} \"At least I will savour the emanations of her soul's eternal agony. Out of my way, mon-keigh!\"",
      "traits": [
        {
          "trait": "Translated",
          "trait_date": "2025-03-06T14:30:46.7339399+00:00",
          "locale_text": "「薄汚い腰抜けめ！」{n}ユリエットを観察していた異種族のひとりが身を乗り出し、彼女の胸から輝く真紅の宝石を引きちぎる。{/n}「この女の魂の永遠の苦しみだけでも味わってやろう。どけ、モン＝ケイ！」",
          "speaker": "DrukhariBandit",
          "speaker_gender": "Male"
        }
      ]
    },
    {
      "locale": "zhCN",
      "text": "“你这没骨气的烂肉！”{n}一个正在观察伊莉耶特的异形俯下身子，从她胸前扯下了那颗闪闪发光的深红色宝石。{/n}“至少我可以永远品尝她灵魂中的痛苦。别挡我的路，猴子！”",
      "modification_date": "2023-10-09T13:10:38.690951+00:00",
      "translated_from": "enGB",
      "translation_date": "2023-10-19T13:01:06.703388+00:00",
      "original_text": "\"Spineless carrion!\" {n}One of the xenos who were observing Yrliet leans forward and tears the radiant crimson gemstone from her chest.{/n} \"At least I will savour the emanations of her soul's eternal agony. Out of my way, mon-keigh!\"",
      "traits": [
        {
          "trait": "Translated",
          "trait_date": "2023-10-19T13:01:06.703389+00:00",
          "locale_text": "“你这没骨气的烂肉！”{n}一个正在观察伊莉耶特的异形俯下身子，从她胸前扯下了那颗闪闪发光的深红色宝石。{/n}“至少我可以永远品尝她灵魂中的痛苦。别挡我的路，猴子！”",
          "speaker": "DrukhariBandit",
          "speaker_gender": "Male"
        }
      ]
    },
    {
      "locale": "esES",
      "text": "«¡Carroña cobarde!». {n}Uno de los xenos que observaban a Yrliet se inclina hacia delante y le arranca la radiante gema carmesí del pecho.{/n} «Al menos saborearé las emanaciones de la agonía eterna de su alma. ¡Fuera de mi camino, mon-keigh!».",
      "modification_date": "2023-11-21T22:57:14.7316927+00:00",
      "translated_from": "enGB",
      "translation_date": "2023-11-21T22:57:14.7316934+00:00",
      "original_text": "\"Spineless carrion!\" {n}One of the xenos who were observing Yrliet leans forward and tears the radiant crimson gemstone from her chest.{/n} \"At least I will savour the emanations of her soul's eternal agony. Out of my way, mon-keigh!\"",
      "traits": [
        {
          "trait": "Translated",
          "trait_date": "2023-11-21T22:57:14.7316967+00:00",
          "locale_text": "«¡Carroña cobarde!». {n}Uno de los xenos que observaban a Yrliet se inclina hacia delante y le arranca la radiante gema carmesí del pecho.{/n} «Al menos saborearé las emanaciones de la agonía eterna de su alma. ¡Fuera de mi camino, mon-keigh!».",
          "speaker": "DrukhariBandit",
          "speaker_gender": "Male"
        }
      ]
    },
    {
      "locale": "deDE",
      "text": "\"Rückgratlose Aasgeier!\" {n}Einer der Xenos, die Yrliet beobachtet haben, beugt sich vor und reißt den strahlend roten Edelstein von ihrer Brust.{/n} \"Endlich kann ich die Ausdünstungen der ewigen Pein ihre Seele kosten. Aus dem Weg, Chem-Pan-Sey!\"",
      "modification_date": "2023-10-17T09:10:37.5544229+00:00",
      "translated_from": "enGB",
      "translation_date": "2023-10-17T09:10:37.5544232+00:00",
      "original_text": "\"Spineless carrion!\" {n}One of the xenos who were observing Yrliet leans forward and tears the radiant crimson gemstone from her chest.{/n} \"At least I will savour the emanations of her soul's eternal agony. Out of my way, mon-keigh!\"",
      "traits": [
        {
          "trait": "Translated",
          "trait_date": "2023-10-17T09:10:37.5544249+00:00",
          "locale_text": "\"Rückgratlose Aasgeier!\" {n}Einer der Xenos, die Yrliet beobachtet haben, beugt sich vor und reißt den strahlend roten Edelstein von ihrer Brust.{/n} \"Endlich kann ich die Ausdünstungen der ewigen Pein ihre Seele kosten. Aus dem Weg, Chem-Pan-Sey!\"",
          "speaker": "DrukhariBandit",
          "speaker_gender": "Male"
        }
      ]
    },
    {
      "locale": "frFR",
      "text": "« Vile charogne ! » {n}L'un des xénos qui observaient Yrliet se penche en avant et arrache la gemme écarlate de sa poitrine.{/n} « Avec ça, au moins, je pourrai savourer l'éternelle agonie de son âme. Hors de mon chemin, mon-keigh ! »",
      "modification_date": "2023-10-17T19:52:29.7797866+00:00",
      "translated_from": "enGB",
      "translation_date": "2023-10-17T19:52:29.7797869+00:00",
      "original_text": "\"Spineless carrion!\" {n}One of the xenos who were observing Yrliet leans forward and tears the radiant crimson gemstone from her chest.{/n} \"At least I will savour the emanations of her soul's eternal agony. Out of my way, mon-keigh!\"",
      "traits": [
        {
          "trait": "Translated",
          "trait_date": "2023-10-17T19:52:29.7797892+00:00",
          "locale_text": "« Vile charogne ! » {n}L'un des xénos qui observaient Yrliet se penche en avant et arrache la gemme écarlate de sa poitrine.{/n} « Avec ça, au moins, je pourrai savourer l'éternelle agonie de son âme. Hors de mon chemin, mon-keigh ! »",
          "speaker": "DrukhariBandit",
          "speaker_gender": "Male"
        }
      ]
    },
    {
      "locale": "trTR",
      "text": "\"Ödlek sıçan!\" {n}Yrliet'i gözlemleyen zenolardan biri, öne eğilerek Yrliet'in göğsündeki ışıltılı ve kızıl renkli taşı söküp alıyor.{/n} \"En azından ruhunun çekeceği ebedî ızdırabın sızıntılarına doyabilirim. Çekil önümden mon-keigh!\"",
      "modification_date": "2024-11-15T12:06:02.161558+00:00",
      "translated_from": "enGB",
      "translation_date": "2024-11-15T12:06:02.1615587+00:00",
      "original_text": "\"Spineless carrion!\" {n}One of the xenos who were observing Yrliet leans forward and tears the radiant crimson gemstone from her chest.{/n} \"At least I will savour the emanations of her soul's eternal agony. Out of my way, mon-keigh!\"",
      "traits": [
        {
          "trait": "Translated",
          "trait_date": "2024-05-20T01:32:04.1489433+00:00",
          "locale_text": "\"Ödlek sıçan!\" {n}Yrliet'i gözlemleyen zenolardan biri, öne eğilerek Yrliet'in göğsündeki ışıltılı ve kızıl renkli değerli taşı söküp alıyor.{/n} \"En azından ruhunun çekeceği ebedî ızdırabın sızıntılarının tadını çıkarabilirim. Çekil önümden mon-keigh!\"",
          "speaker": "DrukhariBandit",
          "speaker_gender": "Male"
        }
      ]
    }
  ],
  "string_traits": []
}