{
  "source": "ruRU",
  "key": "19f143c8-cd92-4c84-a7c4-6ef76d20028f",
  "speaker": "UlfarNPC_Naked",
  "speakerGender": "Male",
  "ownerGuid": "49ee4a204db24314bfec5b507487935d",
  "languages": [
    {
      "locale": "ruRU",
      "text": "{n}Ульфар делает небрежный жест, и двое безмолвных слуг почтительно отступают, дабы не мешать вашей беседе.{/n} \"Эттфатер, я должен поблагодарить тебя за спасение. Мне выпала нелегкая битва\".",
      "modification_date": "2023-05-31T05:43:17.5939031+00:00",
      "traits": []
    },
    {
      "locale": "enGB",
      "text": "{n}With a twitch of his fingers, Ulfar bids the two servants in attendance to step away so as not to intrude on your conversation. They silently retreat.{/n} \"Aett-Vater, I must thank you for saving me. I had a difficult battle.\"",
      "modification_date": "2023-07-21T17:24:14.4136953+03:00",
      "translated_from": "ruRU",
      "translation_date": "2023-07-21T17:24:14.4136955+03:00",
      "original_text": "{n}Ульфар делает небрежный жест, и двое безмолвных слуг почтительно отступают, дабы не мешать вашей беседе.{/n} \"Эттфатер, я должен поблагодарить тебя за спасение. Мне выпала нелегкая битва\".",
      "traits": [
        {
          "trait": "Translated",
          "trait_date": "2023-07-21T17:24:14.4136971+03:00",
          "locale_text": "{n}With a twitch of his fingers, Ulfar bids the two servants in attendance to step away so as not to intrude on your conversation. They silently retreat.{/n} \"Aett-Vater, I must thank you for saving me. I had a difficult battle.\"",
          "speaker": "UlfarNPC_Naked",
          "speaker_gender": "Male"
        },
        {
          "trait": "AD_tr_ed",
          "trait_date": "2023-07-21T17:24:14.4136978+03:00",
          "locale_text": "{n}With a twitch of his fingers, Ulfar bids the two servants in attendance to step away so as not to intrude on your conversation. They silently retreat.{/n} \"Aett-Vater, I must thank you for saving me. I had a difficult battle.\"",
          "speaker": "UlfarNPC_Naked",
          "speaker_gender": "Male"
        },
        {
          "trait": "Edited",
          "trait_date": "2023-07-21T17:28:30.2076396+03:00",
          "locale_text": "{n}With a twitch of his fingers, Ulfar bids the two servants in attendance to step away so as not to intrude on your conversation. They silently retreat.{/n} \"Aett-Vater, I must thank you for saving me. I had a difficult battle.\"",
          "speaker": "UlfarNPC_Naked",
          "speaker_gender": "Male"
        },
        {
          "trait": "Turkish",
          "trait_date": "2024-02-26T15:27:12.9483582+00:00",
          "locale_text": "{n}With a twitch of his fingers, Ulfar bids the two servants in attendance to step away so as not to intrude on your conversation. They silently retreat.{/n} \"Aett-Vater, I must thank you for saving me. I had a difficult battle.\"",
          "speaker": "UlfarNPC_Naked",
          "speaker_gender": "Male"
        }
      ]
    },
    {
      "locale": "zhCN",
      "text": "{n}乌尔法手指抽搐了一下，示意两名仆人离开，不要打扰你们的谈话。仆人们静静地退了出去。{/n}“我必须感谢你救了我一命，狼领。那场战斗非常艰苦。”",
      "modification_date": "2023-08-09T11:12:23.8731693+00:00",
      "translated_from": "enGB",
      "translation_date": "2023-08-09T11:12:23.8731695+00:00",
      "original_text": "{n}With a twitch of his fingers, Ulfar bids the two servants in attendance to step away so as not to intrude on your conversation. They silently retreat.{/n} \"Aett-Vater, I must thank you for saving me. I had a difficult battle.\"",
      "traits": [
        {
          "trait": "Translated",
          "trait_date": "2023-08-09T11:12:23.8731712+00:00",
          "locale_text": "{n}乌尔法手指抽搐了一下，示意两名仆人离开，不要打扰你们的谈话。仆人们静静地退了出去。{/n}“我必须感谢你救了我一命，狼领。那场战斗非常艰苦。”",
          "speaker": "UlfarNPC_Naked",
          "speaker_gender": "Male"
        }
      ]
    },
    {
      "locale": "jaJP",
      "text": "{n}会話を邪魔されまいと、ウルファーは指をぴくぴく動かして供をしているふたりの従者に下がるよう命令する。彼らは黙って後ろに下がる。{/n}「アエット＝ヴァテル、俺を助けてくれたことに礼を言わないとな。厳しい戦いだった」",
      "modification_date": "2023-08-14T09:50:36.6995363+00:00",
      "translated_from": "enGB",
      "translation_date": "2025-07-14T14:39:15.9192523+00:00",
      "original_text": "{n}With a twitch of his fingers, Ulfar bids the two servants in attendance to step away so as not to intrude on your conversation. They silently retreat.{/n} \"Aett-Vater, I must thank you for saving me. I had a difficult battle.\"",
      "traits": [
        {
          "trait": "Translated",
          "trait_date": "2025-07-14T14:39:15.9192529+00:00",
          "locale_text": "{n}会話を邪魔されまいと、ウルファーは指をぴくぴく動かして供をしているふたりの従者に下がるよう命令する。彼らは黙って後ろに下がる。{/n}「アエット＝ヴァテル、俺を助けてくれたことに礼を言わないとな。厳しい戦いだった」",
          "speaker": "UlfarNPC_Naked",
          "speaker_gender": "Male"
        }
      ]
    },
    {
      "locale": "esES",
      "text": "{n}Con un gesto de sus dedos, Ulfar indica a los sirvientes que le asisten que se alejen para no interrumpir vuestra conversación. Se alejan en silencio.{/n} «Aett-Vater, debo darle las gracias por salvarme. Ha sido una batalla difícil».",
      "modification_date": "2023-08-21T16:15:27.1996151+00:00",
      "translated_from": "enGB",
      "translation_date": "2023-08-21T16:15:27.1996152+00:00",
      "original_text": "{n}With a twitch of his fingers, Ulfar bids the two servants in attendance to step away so as not to intrude on your conversation. They silently retreat.{/n} \"Aett-Vater, I must thank you for saving me. I had a difficult battle.\"",
      "traits": [
        {
          "trait": "Translated",
          "trait_date": "2023-08-21T16:15:27.1996156+00:00",
          "locale_text": "{n}Con un gesto de sus dedos, Ulfar indica a los sirvientes que le asisten que se alejen para no interrumpir vuestra conversación. Se alejan en silencio.{/n} «Aett-Vater, debo darle las gracias por salvarme. Ha sido una batalla difícil».",
          "speaker": "UlfarNPC_Naked",
          "speaker_gender": "Male"
        }
      ]
    },
    {
      "locale": "frFR",
      "text": "{n}D'un geste de ses doigts, Ulfar ordonne aux deux serviteurs présents de s'éloigner pour que vous puissiez discuter tranquillement. Ils se retirent en silence.{/n} « Je dois vous remercier de m'avoir sauvé, aett-vater. J'ai livré un combat difficile. »",
      "modification_date": "2023-09-04T14:12:43.181355+00:00",
      "translated_from": "enGB",
      "translation_date": "2023-10-17T19:11:59.9487005+00:00",
      "original_text": "{n}With a twitch of his fingers, Ulfar bids the two servants in attendance to step away so as not to intrude on your conversation. They silently retreat.{/n} \"Aett-Vater, I must thank you for saving me. I had a difficult battle.\"",
      "traits": [
        {
          "trait": "Translated",
          "trait_date": "2023-10-17T19:11:59.9487031+00:00",
          "locale_text": "{n}D'un geste de ses doigts, Ulfar ordonne aux deux serviteurs présents de s'éloigner pour que vous puissiez discuter tranquillement. Ils se retirent en silence.{/n} « Je dois vous remercier de m'avoir sauvé, aett-vater. J'ai livré un combat difficile. »",
          "speaker": "UlfarNPC_Naked",
          "speaker_gender": "Male"
        }
      ]
    },
    {
      "locale": "deDE",
      "text": "{n}Mit einem Fingerschnippen schickt Ulfar die zwei anwesenden Diener weg, damit niemand euer Gespräch stört. Sie ziehen sich schweigend zurück.{/n} \"Aett-Vater, ich muss Euch danken, dass Ihr mich gerettet habt. Ich hatte einen schweren Kampf.\"",
      "modification_date": "2023-10-16T13:29:15.7152748+00:00",
      "translated_from": "enGB",
      "translation_date": "2023-10-16T13:29:15.7152751+00:00",
      "original_text": "{n}With a twitch of his fingers, Ulfar bids the two servants in attendance to step away so as not to intrude on your conversation. They silently retreat.{/n} \"Aett-Vater, I must thank you for saving me. I had a difficult battle.\"",
      "traits": [
        {
          "trait": "Translated",
          "trait_date": "2023-10-16T13:29:15.7152772+00:00",
          "locale_text": "{n}Mit einem Fingerschnippen schickt Ulfar die zwei anwesenden Diener weg, damit niemand euer Gespräch stört. Sie ziehen sich schweigend zurück.{/n} \"Aett-Vater, ich muss Euch danken, dass Ihr mich gerettet habt. Ich hatte einen schweren Kampf.\"",
          "speaker": "UlfarNPC_Naked",
          "speaker_gender": "Male"
        }
      ]
    },
    {
      "locale": "trTR",
      "text": "{n}Ulfar, parmaklarıyla orada bulunan hizmetkârlara konuşmanızı bölmemeleri için dışarı çıkmalarını emrediyor. Sessizce gözden kayboluyorlar.{/n} \"Aett-Vater, beni kurtardığın için sana teşekkür borçluyum. Zor bir savaştı.\"",
      "modification_date": "2024-11-15T12:06:57.3406196+00:00",
      "translated_from": "enGB",
      "translation_date": "2024-11-15T12:06:57.3406203+00:00",
      "original_text": "{n}With a twitch of his fingers, Ulfar bids the two servants in attendance to step away so as not to intrude on your conversation. They silently retreat.{/n} \"Aett-Vater, I must thank you for saving me. I had a difficult battle.\"",
      "traits": [
        {
          "trait": "Translated",
          "trait_date": "2024-05-20T01:32:15.387003+00:00",
          "locale_text": "{n}Ulfar, parmaklarını oynatarak orada bulunan hizmetkârlara konuşmanızı bölmemeleri için dışarı çıkmalarını emrediyor. Sessizce gözden kayboluyorlar.{/n} \"Aett-Vater, beni kurtardığın için sana bir teşekkür borçluyum. Zor bir savaş geçirdim.\"",
          "speaker": "UlfarNPC_Naked",
          "speaker_gender": "Male"
        }
      ]
    }
  ],
  "string_traits": []
}