{
  "source": "ruRU",
  "key": "3287ec8d-f979-4e91-bc83-b4948894caf2",
  "speaker": "Opticon22",
  "speakerGender": "Male",
  "ownerGuid": "ce44ed29b0214ecca4b2a931fe994762",
  "languages": [
    {
      "locale": "ruRU",
      "text": "\"Запрос отклонен. Технобрат Тарзус прошел процедуру санктификации и наделен реликварными привилегиями. Я //не имею полномочий//имею недостаточный уровень допуска//, чтобы осуществлять командование данной единицей\". {n}В голосе Опктикона-22 чудится намек на неприязнь к кровожадному техножрецу.{/n}",
      "modification_date": "2024-02-05T20:35:51.2802578+00:00",
      "translation_comment": "",
      "traits": []
    },
    {
      "locale": "enGB",
      "text": "\"Request denied. Tech-Brother Tarzus has passed sanctification and has relic privileges. I lack the //authority//access level necessary// to command this unit.\" {n}There is a hint of animosity toward the bloodthirsty Tech-Priest in Opticon-22's voice.{/n}",
      "modification_date": "2023-12-14T08:36:15.5428066+00:00",
      "translation_comment": "",
      "translated_from": "ruRU",
      "translation_date": "2023-12-14T08:36:15.5428072+00:00",
      "original_text": "\"Запрос отклонен. Технобрат Тарзус прошел процедуру санктификации и наделен реликварными привилегиями. Я //не имею полномочий//имею недостаточный уровень допуска//, чтобы осуществлять командование данной единицей\". {n}В голосе Опктикона-22 чудится намек на неприязнь к кровожадному техножрецу.{/n}",
      "traits": [
        {
          "trait": "Translated",
          "trait_date": "2023-05-12T13:06:19.380554+03:00",
          "locale_text": "\"Request declined. Tech-Brother Tarzus has passed sanctification and has relic privileges. I lack the //authority//access level necessary// to command this unit.\" {n}There's a hint of animosity toward the bloodthirsty Tech-Priest in Opticon-22's voice.{/n}",
          "speaker": "Opticon22",
          "speaker_gender": "Male"
        },
        {
          "trait": "NE_tr",
          "trait_date": "2023-05-12T13:06:19.3805546+03:00",
          "locale_text": "\"Request declined. Tech-Brother Tarzus has passed sanctification and has relic privileges. I lack the //authority//access level necessary// to command this unit.\" {n}There's a hint of animosity toward the bloodthirsty Tech-Priest in Opticon-22's voice.{/n}",
          "speaker": "Opticon22",
          "speaker_gender": "Male"
        },
        {
          "trait": "Edited",
          "trait_date": "2023-09-07T12:43:36.7102685+00:00",
          "locale_text": "\"Request declined. Tech-Brother Tarzus has passed sanctification and has relic privileges. I lack the //authority//access level necessary// to command this unit.\" {n}There's a hint of animosity toward the bloodthirsty Tech-Priest in Opticon-22's voice.{/n}",
          "speaker": "Opticon22",
          "speaker_gender": "Male"
        },
        {
          "trait": "LG_ed",
          "trait_date": "2023-09-07T12:43:36.710269+00:00",
          "locale_text": "\"Request declined. Tech-Brother Tarzus has passed sanctification and has relic privileges. I lack the //authority//access level necessary// to command this unit.\" {n}There's a hint of animosity toward the bloodthirsty Tech-Priest in Opticon-22's voice.{/n}",
          "speaker": "Opticon22",
          "speaker_gender": "Male"
        },
        {
          "trait": "AD_rv",
          "trait_date": "2023-12-14T08:36:15.5428094+00:00",
          "locale_text": "\"Request denied. Tech-Brother Tarzus has passed sanctification and has relic privileges. I lack the //authority//access level necessary// to command this unit.\" {n}There is a hint of animosity toward the bloodthirsty Tech-Priest in Opticon-22's voice.{/n}",
          "speaker": "Opticon22",
          "speaker_gender": "Male"
        },
        {
          "trait": "Turkish",
          "trait_date": "2024-02-26T15:27:11.1861539+00:00",
          "locale_text": "\"Request denied. Tech-Brother Tarzus has passed sanctification and has relic privileges. I lack the //authority//access level necessary// to command this unit.\" {n}There is a hint of animosity toward the bloodthirsty Tech-Priest in Opticon-22's voice.{/n}",
          "speaker": "Opticon22",
          "speaker_gender": "Male"
        }
      ]
    },
    {
      "locale": "jaJP",
      "text": "「リクエスト却下。技術同胞ターザスは聖別に成功し、聖遺物の特権を所有。このユニットを指揮する//権限//上で必要なレベル//を私は持っていない」{n}オプティコン-22の声には殺気だった技術司祭への敵意に関するヒントが仄めかされていた。{/n}",
      "modification_date": "2025-07-14T14:38:32.583898+00:00",
      "translation_comment": "",
      "translated_from": "enGB",
      "translation_date": "2025-07-14T14:38:32.5838981+00:00",
      "original_text": "\"Request denied. Tech-Brother Tarzus has passed sanctification and has relic privileges. I lack the //authority//access level necessary// to command this unit.\" {n}There is a hint of animosity toward the bloodthirsty Tech-Priest in Opticon-22's voice.{/n}",
      "traits": [
        {
          "trait": "Translated",
          "trait_date": "2025-07-14T14:38:32.5838987+00:00",
          "locale_text": "「リクエスト却下。技術同胞ターザスは聖別に成功し、聖遺物の特権を所有。このユニットを指揮する//権限//上で必要なレベル//を私は持っていない」{n}オプティコン-22の声には殺気だった技術司祭への敵意に関するヒントが仄めかされていた。{/n}",
          "speaker": "Opticon22",
          "speaker_gender": "Male"
        }
      ]
    },
    {
      "locale": "zhCN",
      "text": "“请求已拒绝。技术兄弟塔祖斯已经通过了圣化过程，拥有管理圣物的特权。我缺乏指挥此单位所必需的//权限//访问级别//。”{n}奥普蒂孔22号的语气表明，他对嗜血的塔祖斯带着一丝敌意。{/n}",
      "modification_date": "2023-10-25T08:01:22.8606683+00:00",
      "translation_comment": "",
      "translated_from": "enGB",
      "translation_date": "2024-03-25T13:52:25.0591459+00:00",
      "original_text": "\"Request denied. Tech-Brother Tarzus has passed sanctification and has relic privileges. I lack the //authority//access level necessary// to command this unit.\" {n}There is a hint of animosity toward the bloodthirsty Tech-Priest in Opticon-22's voice.{/n}",
      "traits": [
        {
          "trait": "Translated",
          "trait_date": "2023-10-25T08:01:22.8606698+00:00",
          "locale_text": "“请求已拒绝。技术兄弟塔祖斯已经通过了圣化过程，拥有管理圣物的特权。我缺乏指挥此单位所必需的//权限//访问级别//。”{n}奥普蒂孔22号的语气表明，他对嗜血的塔祖斯带着一丝敌意。{/n}",
          "speaker": "Opticon22",
          "speaker_gender": "Male"
        }
      ]
    },
    {
      "locale": "deDE",
      "text": "\"Anfrage abgewiesen. Tech-Bruder Tarzus hat die Heiligung abgeschlossen und besitzt Reliktprivilegien. Ich habe nicht die //Autorität//erforderliche Freigabestufe//, um dieser Einheit Befehle zu erteilen.\" {n}In der Stimme von Opticon-22 liegt ein Hauch von Ablehnung gegenüber dem blutrünstigen Techpriester.{/n}",
      "modification_date": "2023-10-16T13:28:41.1807572+00:00",
      "translation_comment": "",
      "translated_from": "enGB",
      "translation_date": "2024-03-18T15:26:45.5169588+00:00",
      "original_text": "\"Request denied. Tech-Brother Tarzus has passed sanctification and has relic privileges. I lack the //authority//access level necessary// to command this unit.\" {n}There is a hint of animosity toward the bloodthirsty Tech-Priest in Opticon-22's voice.{/n}",
      "traits": [
        {
          "trait": "Translated",
          "trait_date": "2023-10-16T13:28:41.1807587+00:00",
          "locale_text": "\"Anfrage abgewiesen. Tech-Bruder Tarzus hat die Heiligung abgeschlossen und besitzt Reliktprivilegien. Ich habe nicht die //Autorität//erforderliche Freigabestufe//, um dieser Einheit Befehle zu erteilen.\" {n}In der Stimme von Opticon-22 liegt ein Hauch von Ablehnung gegenüber dem blutrünstigen Techpriester.{/n}",
          "speaker": "Opticon22",
          "speaker_gender": "Male"
        }
      ]
    },
    {
      "locale": "frFR",
      "text": "« Demande refusée. Le technofrère Tarzus a obtenu sa sanctification et bénéficie en tant que tel des privilèges octroyés aux seules reliques. Je n'ai pas //l'autorité//le niveau d'accréditation nécessaire// pour donner des ordres à cette unité. » {n}Vous décelez dans la voix d'Opticon-22 une pointe d'animosité envers le technoprêtre sanguinaire.{/n}",
      "modification_date": "2023-11-02T09:40:45.8053115+00:00",
      "translation_comment": "",
      "translated_from": "enGB",
      "translation_date": "2024-01-16T12:57:09.9204298+00:00",
      "original_text": "\"Request denied. Tech-Brother Tarzus has passed sanctification and has relic privileges. I lack the //authority//access level necessary// to command this unit.\" {n}There is a hint of animosity toward the bloodthirsty Tech-Priest in Opticon-22's voice.{/n}",
      "traits": [
        {
          "trait": "Translated",
          "trait_date": "2023-11-02T09:40:45.8053128+00:00",
          "locale_text": "« Demande refusée. Le technofrère Tarzus a obtenu sa sanctification et bénéficie en tant que tel des privilèges octroyés aux seules reliques. Je n'ai pas //l'autorité//le niveau d'accréditation nécessaire// pour donner des ordres à cette unité. » {n}Vous décelez dans la voix d'Opticon-22 une pointe d'animosité envers le technoprêtre sanguinaire.{/n}",
          "speaker": "Opticon22",
          "speaker_gender": "Male"
        }
      ]
    },
    {
      "locale": "esES",
      "text": "«Solicitud denegada. El tecnohermano Tarzus ha completado su santificación y ha recibido privilegios de reliquia. Carezco de //la autoridad//el nivel de acceso necesario// para tomar el control de esta unidad». {n}Notas un deje de hostilidad hacia el sanguinario tecnosacerdote en la voz de Opticon-22.{/n}",
      "modification_date": "2023-10-18T14:18:11.3172599+00:00",
      "translation_comment": "",
      "translated_from": "enGB",
      "translation_date": "2024-02-26T17:29:03.7276522+00:00",
      "original_text": "\"Request denied. Tech-Brother Tarzus has passed sanctification and has relic privileges. I lack the //authority//access level necessary// to command this unit.\" {n}There is a hint of animosity toward the bloodthirsty Tech-Priest in Opticon-22's voice.{/n}",
      "traits": [
        {
          "trait": "Translated",
          "trait_date": "2023-10-18T14:18:11.317262+00:00",
          "locale_text": "«Solicitud denegada. El tecnohermano Tarzus ha completado su santificación y ha recibido privilegios de reliquia. Carezco de //la autoridad//el nivel de acceso necesario// para tomar el control de esta unidad». {n}Notas un deje de hostilidad hacia el sanguinario tecnosacerdote en la voz de Opticon-22.{/n}",
          "speaker": "Opticon22",
          "speaker_gender": "Male"
        }
      ]
    },
    {
      "locale": "trTR",
      "text": "\"Talep reddedildi. Tekno Kardeş Tarzus, takdisini geçmiş olup yadigâr imtiyazlarına sahiptir. Bu birime emir vermek için gereken //yetkiye//erişim seviyesine// sahip değilim.\" {n}Opticon-22'nin sesinde, kana susamış Tekno Rahip'e karşı duyduğu düşmanlık sezilebiliyor.{/n}",
      "modification_date": "2024-11-15T12:06:39.2533416+00:00",
      "translated_from": "enGB",
      "translation_date": "2024-11-15T12:06:39.2533424+00:00",
      "original_text": "\"Request denied. Tech-Brother Tarzus has passed sanctification and has relic privileges. I lack the //authority//access level necessary// to command this unit.\" {n}There is a hint of animosity toward the bloodthirsty Tech-Priest in Opticon-22's voice.{/n}",
      "traits": [
        {
          "trait": "Translated",
          "trait_date": "2024-05-20T01:32:13.020137+00:00",
          "locale_text": "\"Talep reddedildi. Tekno Kardeş Tarzus, takdisini geçti ve yadigâr imtiyazlarına sahip. Bu birime emir vermek için gereken //yetkiye//erişim seviyesine// sahip değilim.\" {n}Opticon-22'nin sesinde, kana susamış Tekno Rahip'e karşı bir düşmanlık sezilebiliyor.{/n}",
          "speaker": "Opticon22",
          "speaker_gender": "Male"
        }
      ]
    }
  ],
  "string_traits": []
}