{
  "source": "ruRU",
  "key": "8b7e680b-9fde-4cf7-9bf5-211ba77a914f",
  "ownerGuid": "c50af302904e49d0b612f518b271bbd4",
  "languages": [
    {
      "locale": "ruRU",
      "text": "\"Пусть спорщики выставят представителей и попытаются договориться, как им сосуществовать\".",
      "modification_date": "2023-07-18T14:50:15.6393181+00:00",
      "traits": []
    },
    {
      "locale": "enGB",
      "text": "\"Let them bring forth their representatives and try to negotiate some form of coexistence.\"",
      "modification_date": "2023-09-11T10:33:53.7712453+00:00",
      "translated_from": "ruRU",
      "translation_date": "2024-11-18T09:59:48.2391806+00:00",
      "original_text": "\"Пусть спорщики выставят представителей и попытаются договориться, как им сосуществовать\".",
      "traits": [
        {
          "trait": "Translated",
          "trait_date": "2023-08-04T05:18:28.2935879+00:00",
          "locale_text": "\"Let the debaters put out their representatives and try to negotiate their coexistence.\""
        },
        {
          "trait": "FG_tr",
          "trait_date": "2023-08-04T05:18:28.2935883+00:00",
          "locale_text": "\"Let the debaters put out their representatives and try to negotiate their coexistence.\""
        },
        {
          "trait": "Edited",
          "trait_date": "2023-09-11T10:33:53.7712486+00:00",
          "locale_text": "\"Let them bring forth their representatives and try to negotiate some form of coexistence.\""
        },
        {
          "trait": "JL_ed",
          "trait_date": "2023-09-11T10:33:53.7712492+00:00",
          "locale_text": "\"Let them bring forth their representatives and try to negotiate some form of coexistence.\""
        },
        {
          "trait": "Turkish",
          "trait_date": "2024-07-16T08:48:19.1192909+00:00",
          "locale_text": "\"Let them bring forth their representatives and try to negotiate some form of coexistence.\""
        },
        {
          "trait": "TK_rv",
          "trait_date": "2024-11-18T09:59:48.2391847+00:00",
          "locale_text": "\"Let them bring forth their representatives and try to negotiate some form of coexistence.\""
        }
      ]
    },
    {
      "locale": "zhCN",
      "text": "“让他们各自派出自己的代表，通过谈判达成某种形式的共存吧。”",
      "modification_date": "2023-11-01T11:03:59.9041807+00:00",
      "translated_from": "enGB",
      "translation_date": "2023-11-01T11:03:59.9041813+00:00",
      "original_text": "\"Let them bring forth their representatives and try to negotiate some form of coexistence.\"",
      "traits": [
        {
          "trait": "Translated",
          "trait_date": "2023-11-01T11:03:59.9041825+00:00",
          "locale_text": "“让他们各自派出自己的代表，通过谈判达成某种形式的共存吧。”"
        }
      ]
    },
    {
      "locale": "esES",
      "text": "«Que traigan a sus representantes e intenten negociar alguna forma de coexistencia».",
      "modification_date": "2023-10-02T15:43:28.0860479+00:00",
      "translated_from": "enGB",
      "translation_date": "2023-10-02T15:43:28.0860481+00:00",
      "original_text": "\"Let them bring forth their representatives and try to negotiate some form of coexistence.\"",
      "traits": [
        {
          "trait": "Translated",
          "trait_date": "2023-10-02T15:43:28.0860489+00:00",
          "locale_text": "«Que traigan a sus representantes e intenten negociar alguna forma de coexistencia»."
        }
      ]
    },
    {
      "locale": "jaJP",
      "text": "「代表者を連れて行かせ、共存のための交渉を試すようにさせよう」",
      "modification_date": "2023-10-16T09:55:23.1924107+00:00",
      "translated_from": "enGB",
      "translation_date": "2023-10-27T09:58:05.9777691+00:00",
      "original_text": "\"Let them bring forth their representatives and try to negotiate some form of coexistence.\"",
      "traits": [
        {
          "trait": "Translated",
          "trait_date": "2023-10-27T09:58:05.9777711+00:00",
          "locale_text": "「代表者を連れて行かせ、共存のための交渉を試すようにさせよう」"
        }
      ]
    },
    {
      "locale": "frFR",
      "text": "« Qu'ils dépêchent des émissaires afin de négocier des conditions de coexistence pacifique. »",
      "modification_date": "2023-11-19T21:10:41.3824835+00:00",
      "translated_from": "enGB",
      "translation_date": "2023-11-19T21:10:41.3824844+00:00",
      "original_text": "\"Let them bring forth their representatives and try to negotiate some form of coexistence.\"",
      "traits": [
        {
          "trait": "Translated",
          "trait_date": "2023-11-19T21:10:41.3824874+00:00",
          "locale_text": "« Qu'ils dépêchent des émissaires afin de négocier des conditions de coexistence pacifique. »"
        }
      ]
    },
    {
      "locale": "deDE",
      "text": "\"Lasst sie ihre Vertreter bringen, und versuchen wir, eine Form der Koexistenz auszuhandeln.\"",
      "modification_date": "2023-10-23T09:47:26.4399602+00:00",
      "translated_from": "enGB",
      "translation_date": "2023-10-23T09:47:26.4399607+00:00",
      "original_text": "\"Let them bring forth their representatives and try to negotiate some form of coexistence.\"",
      "traits": [
        {
          "trait": "Translated",
          "trait_date": "2023-10-23T09:47:26.4399623+00:00",
          "locale_text": "\"Lasst sie ihre Vertreter bringen, und versuchen wir, eine Form der Koexistenz auszuhandeln.\""
        }
      ]
    },
    {
      "locale": "trTR",
      "text": "\"Temsilcilerini huzuruma getirsinler. Birlikte yaşayabilecekleri bir model üzerine görüşmeye çalışalım.\"",
      "modification_date": "2024-11-15T11:56:00.8742822+00:00",
      "translated_from": "enGB",
      "translation_date": "2024-11-15T11:56:00.8742825+00:00",
      "original_text": "\"Let them bring forth their representatives and try to negotiate some form of coexistence.\""
    }
  ],
  "string_traits": []
}